chatgpt/__init__.py
chatgpt/__main__.py
chatgpt/api.py
chatgpt/cli.py
chatgpt/const.py
chatgpt/exceptions.py
chatgpt/payloads.py
chatgpt_api-0.2.1.dist-info/LICENSE
chatgpt_api-0.2.1.dist-info/METADATA
chatgpt_api-0.2.1.dist-info/WHEEL
chatgpt_api-0.2.1.dist-info/entry_points.txt
chatgpt_api-0.2.1.dist-info/top_level.txt
chatgpt_api-0.2.1.dist-info/RECORD
