Metadata-Version: 2.1
Name: chatgpt-api
Version: 0.2.1
Summary: ChatGPT HTTP API Client and CLI
Home-page: https://github.com/mbroton/chatgpt-api
Author: Michal Broton
Author-email: michal@broton.dev
Classifier: Programming Language :: Python :: 3
Classifier: Programming Language :: Python :: 3 :: Only
Classifier: Programming Language :: Python :: Implementation :: CPython
Classifier: Programming Language :: Python :: Implementation :: PyPy
Requires-Python: >=3.7
License-File: LICENSE
